vimms/Agent.py
vimms/BOMAS.py
vimms/Box.py
vimms/BoxManager.py
vimms/BoxVisualise.py
vimms/ChemicalSamplers.py
vimms/Chemicals.py
vimms/ChineseRestaurantProcess.py
vimms/Chromatograms.py
vimms/Column.py
vimms/Common.py
vimms/Controller/__init__.py
vimms/Controller/abc.py
vimms/Controller/base.py
vimms/Controller/box.py
vimms/Controller/dia.py
vimms/Controller/fullscan.py
vimms/Controller/misc.py
vimms/Controller/model.py
vimms/Controller/noise.py
vimms/Controller/roi.py
vimms/Controller/targeted.py
vimms/Controller/topN.py
vimms/DDA_vs_DIA.py
vimms/DIA.py
vimms/Drift.py
vimms/DriftCorrection.py
vimms/DsDA.py
vimms/Environment.py
vimms/Evaluation.py
vimms/Exclusion.py
vimms/Experiment.py
vimms/FeatureExtraction.py
vimms/InSilicoSimulation.py
vimms/MassSpec.py
vimms/MassSpecUtils.py
vimms/Matching.py
vimms/MzmlWriter.py
vimms/Noise.py
vimms/PeakPicking.py
vimms/Roi.py
vimms/Utils.py
vimms/__init__.py
vimms/scripts/DDA_vs_DIA.py
vimms/scripts/__init__.py
vimms/scripts/box_controller.py
vimms/scripts/check_file_sizes.py
vimms/scripts/check_fragmented_ions.py
vimms/scripts/check_ms2_matches.py
vimms/scripts/check_score_threshold_1E4_hela.py
vimms/scripts/config/SmartROI_config.txt
vimms/scripts/config/TopN_config.txt
vimms/scripts/config/WeightedDEW_config.txt
vimms/scripts/config/replicates/SmartROI_config.txt
vimms/scripts/config/replicates/TopN_config.txt
vimms/scripts/config/replicates/WeightedDEW_config.txt
vimms/scripts/data_generation.py
vimms/scripts/debug_chems.py
vimms/scripts/dsda_script.R
vimms/scripts/generate_test_fixtures.py
vimms/scripts/in_silico_optimise.py
vimms/scripts/ms2_database_matching.py
vimms/scripts/msdial_wrapper.py
vimms/scripts/multi_sample_experiment.py
vimms/scripts/mzml_summarise.py
vimms/scripts/openms_batch_feature_finder.sh
vimms/scripts/openms_evaluate.py
vimms/scripts/openms_feature_finder.sh
vimms/scripts/openms_optimise.py
vimms/scripts/openms_optimise_params.py
vimms/scripts/optimal_performance.py
vimms/scripts/parse_txt.py
vimms-2.1.6.dist-info/LICENSE
vimms-2.1.6.dist-info/METADATA
vimms-2.1.6.dist-info/WHEEL
vimms-2.1.6.dist-info/RECORD
