Metadata-Version: 2.3
Name: vimms
Version: 2.1.6
Summary: A framework to develop, test and optimise fragmentation strategies in LC-MS metabolomics.
License: MIT
Keywords: LC-MS,metabolomics,simulator,mass spectrometry
Author: Joe Wandy
Author-email: joe.wandy@glasgow.ac.uk
Requires-Python: >=3.11,<3.13
Classifier: License :: OSI Approved :: MIT License
Classifier: Operating System :: OS Independent
Classifier: Programming Language :: Python :: 3
Classifier: Programming Language :: Python :: 3.11
Classifier: Programming Language :: Python :: 3.12
Requires-Dist: events (>=0.5,<0.6)
Requires-Dist: intervaltree (>=3.1.0,<4.0.0)
Requires-Dist: ipyparallel (>=9.0.1,<10.0.0)
Requires-Dist: joblib (>=1.5.1,<2.0.0)
Requires-Dist: jsonpickle (>=4.1.1,<5.0.0)
Requires-Dist: loguru (>=0.7.3,<0.8.0)
Requires-Dist: mass-spec-utils (>=0.0.12,<0.0.13)
Requires-Dist: matplotlib (>=3.10.3,<4.0.0)
Requires-Dist: networkx (>=3.5,<4.0)
Requires-Dist: numba (>=0.61.2,<0.62.0)
Requires-Dist: numba-stats (>=1.10.1,<2.0.0)
Requires-Dist: numpy (>=2.2.6,<3.0.0)
Requires-Dist: optuna (>=4.3.0,<5.0.0)
Requires-Dist: pandas (>=2.2.3,<3.0.0)
Requires-Dist: plotly (>=6.1.2,<7.0.0)
Requires-Dist: psims (>=1.3.5,<2.0.0)
Requires-Dist: pymzml (>=2.5.11,<3.0.0)
Requires-Dist: pysmiles (>=2.0.0,<3.0.0)
Requires-Dist: requests (>=2.32.3,<3.0.0)
Requires-Dist: scikit-learn (>=1.6.1,<2.0.0)
Requires-Dist: scipy (>=1.15.3,<2.0.0)
Requires-Dist: seaborn (>=0.13.2,<0.14.0)
Requires-Dist: statsmodels (>=0.14.4,<0.15.0)
Requires-Dist: tabulate (>=0.9.0,<0.10.0)
Requires-Dist: tqdm (>=4.67.1,<5.0.0)
Project-URL: Homepage, https://github.com/glasgowcompbio/vimms
